Workbook

Sheet 00_Architecture_Overview
A1: AI-NATIVE ENTERPRISE ARCHITECTURE · PROFESSIONAL SERVICES (CORPORATE SERVICE PROVIDER)
A2: Department OS · Full 6-Layer Stack · Document Registry · Spec Requirements
A3: # | B3: Layer | C3: Name | D3: Purpose / Function | E3: Primary Outputs | F3: Key Gap (most cos miss) | G3: Priority | H3: Owner Type | I3: Doc Template
A4: L6 | B4: Interaction Surface | C4: All touchpoints between humans and the AI system: client portal, internal chat, email, API endpoints, embedded widgets | D4: UX_SPEC.md per channel; channel capability matrix; fallback/escalation map | E4: Inconsistent channel behavior; no defined fallback when agent fails | F4: HIGH | G4: Product / Design | H4: UX_SPEC.md
A5: L5 | B5: Agent Layer | C5: Named agents with defined roles, tool permissions, memory access, and escalation logic. Orchestrator routes to specialist sub-agents | D5: AGENT_SPEC.md per agent; inter-agent routing map; audit log schema | E5: No orchestration logic; agents are isolated and can't hand off | F5: HIGH | G5: AI / Engineering | H5: AGENT_SPEC.md
A6: L4 | B6: Skill & Workflow Layer | C6: Atomic, reusable capabilities (SKILL.md) composed into multi-step workflows with human-in-the-loop gates and eval test cases | D6: SKILL.md files; WORKFLOW.md; EVAL.json per skill; prompt library | E6: No eval system; skills deployed without correctness checks | F6: HIGH | G6: Operations / AI | H6: SKILL.md + WORKFLOW.md
A7: L3 | B7: Integration & Tool Layer | C7: All external connections: MCP servers, CRM, document systems, regulatory data feeds, registry APIs, banking APIs | D7: TOOL_REGISTRY.md; permission matrix; auth credential map; rate limit log | E7: No tool governance; any agent can call any tool with no audit trail | F7: MEDIUM | G7: Engineering / IT | H7: TOOL_REGISTRY.md
A8: L2 | B8: Memory & Context Layer | C8: Four memory types: episodic (per-client session history), semantic (SOPs, procedures), procedural (skill execution patterns), working (in-flight context) | D8: MEMORY_SCHEMA.md; retention policy; context window management rules | E8: No persistent memory; each session starts cold with zero context | F8: HIGH | G8: AI / Engineering | H8: MEMORY_SCHEMA.md
A9: L1 | B9: Knowledge Foundation (GraphRAG) | C9: Entity graph + relationship graph + document corpus indexed for graph-aware retrieval. Critical for professional services: ownership chains, jurisdiction rules, conflict-of-interest paths cannot be answered by flat vector search | D9: GRAPH_SCHEMA.md; CORPUS_INDEX.md; entity taxonomy; relationship type registry | E9: Using vanilla RAG on flat documents — loses all relational/jurisdictional reasoning | F9: CRITICAL | G9: Data / Knowledge | H9: GRAPH_SCHEMA.md
A10: Cross-cutting documents (not layer-specific): DEPARTMENT_OS_MAP.md — master index linking all layers and teams | GOVERNANCE.md — approval matrix, change management, audit trail, AI policy

Sheet 01_Document_Registry
A1: DOCUMENT REGISTRY · AI-Native Architecture — All 8 Document Types
A2: Every document maps to one or more architecture layers. Each has defined owner, trigger, required sections, and validation criteria.
A3: # | B3: Document Type | C3: Layer(s) | D3: Format | E3: Owner Role | F3: Trigger (when to create/update) | G3: Required Sections | H3: Validation Criteria | I3: Review Cadence | J3: Status | K3: Priority
A4: 1 | B4: UX_SPEC.md | C4: L6 | D4: Markdown | E4: Product / Design | F4: New channel added OR interaction pattern changes | G4: Channel description · Input/output contract · Fallback behavior · Escalation triggers · Example conversation flows · Error messages | H4: Every channel has defined fallback · No undefined error states · Escalation paths tested | I4: Per channel launch | J4: Template | K4: MEDIUM
A5: 2 | B5: AGENT_SPEC.md | C5: L5 | D5: Markdown + YAML | E5: AI Lead / Eng | F5: New agent deployed OR agent role changes OR tool permissions change | G5: Agent name & role · System prompt (versioned) · Tool access list · Memory read/write scope · Escalation rules · Inter-agent routing · Risk level · Audit log requirements | H5: No undefined tool permissions · Escalation always reachable · Risk level matches approval gate | I5: Per agent deploy | J5: Template | K5: HIGH
A6: 3 | B6: SKILL.md | C6: L4 | D6: Markdown | E6: Operations / AI | F6: New repeatable task identified OR skill behavior changes | G6: name (identifier) · description (trigger phrases) · input format · output format · step-by-step logic · dependencies · human-in-loop gates · eval criteria | H6: Trigger phrases tested against eval set · Input/output formats machine-parseable · Zero ambiguous steps | I6: Per skill change | J6: Template | K6: HIGH
A7: 4 | B7: WORKFLOW.md | C7: L4 | D7: Markdown + Mermaid | E7: Operations | F7: Multi-step process involving >1 skill or >1 agent | G7: Workflow name · Trigger · Steps (skill/agent/human) · Decision gates · Inputs per step · Outputs per step · Error handling · SLA/timeout | H7: Every step has defined owner · All gates have accept/reject criteria · Error paths documented | I7: Per workflow change | J7: Template | K7: HIGH
A8: 5 | B8: EVAL.json | C8: L4 | D8: JSON | E8: AI / QA | F8: After every SKILL.md or WORKFLOW.md is created or updated | G8: skill_id · test_cases (input + expected_output + pass_criteria) · baseline_score · current_score · last_run_date · failure_log | H8: ≥10 test cases per skill · Pass rate ≥ 90% before deploy · Regression check on every update | I8: Every deploy | J8: Template | K8: HIGH
A9: 6 | B9: TOOL_REGISTRY.md | C9: L3 | D9: Markdown + Table | E9: Engineering / IT | F9: New tool/MCP server added OR permissions change | G9: Tool name · Type (MCP / API / internal) · Auth method · Agents permitted · Data accessed · Rate limits · Fallback if unavailable · Cost per call | H9: Every agent references only registered tools · Auth credentials documented · Rate limits enforced | I9: Monthly audit | J9: Template | K9: MEDIUM
A10: 7 | B10: MEMORY_SCHEMA.md | C10: L2 | D10: Markdown + JSON Schema | E10: AI / Engineering | F10: Memory architecture designed OR retention policy changes | G10: Memory types (episodic / semantic / procedural / working) · Schema per type · Retention policy · Access control · Indexing strategy · PII handling | H10: Retention periods comply with data policy · PII fields masked · All 4 memory types defined | I10: Quarterly review | J10: Template | K10: HIGH
A11: 8 | B11: GRAPH_SCHEMA.md | C11: L1 | D11: Markdown + JSON Schema | E11: Data / Knowledge | F11: Knowledge graph initialized OR new entity/relationship type added | G11: Entity types (with properties) · Relationship types (with directionality + cardinality) · Source corpus · Indexing pipeline · Query patterns · Update cadence · Conflict resolution | H11: All entity types have unique identifiers · Relationship types have defined direction · Query patterns validated against sample data | I11: Per schema change | J11: Template | K11: CRITICAL
A12: 9 | B12: CORPUS_INDEX.md | C12: L1 | D12: Markdown + Table | E12: Data / Knowledge | F12: New document source added to knowledge base | G12: Source name · Document type · Jurisdiction scope · Update frequency · Indexing method · Quality score · Last updated · Responsible owner | H12: Every source has defined update owner · Stale threshold defined · Deduplication strategy documented | I12: Monthly | J12: Template | K12: HIGH
A13: 10 | B13: DEPARTMENT_OS_MAP.md | C13: L1–L6 | D13: Markdown | E13: Chief of Staff / AI Lead | F13: Quarterly review OR major architecture change | G13: Department name · Layer inventory (links to all docs) · Agent roster · Skill count · Workflow count · Knowledge graph status · Open gaps · Roadmap | H13: All layers have at least one document · No orphaned skills or agents · Roadmap aligned to business goals | I13: Quarterly | J13: Template | K13: HIGH
A14: 11 | B14: GOVERNANCE.md | C14: Cross-cutting | D14: Markdown | E14: Legal / Compliance / AI Lead | F14: AI system goes live OR policy changes OR incident occurs | G14: Approval matrix · Change management process · Incident response · Audit trail requirements · AI use policy · Data retention · Human override procedures | H14: Every agent has named approver · Incident response tested · Audit logs retained per policy | I14: Bi-annual + incident-driven | J14: Template | K14: HIGH

Sheet 02_L1_GraphRAG_Spec
A1: L1 — GRAPHRAG SPECIFICATION · Entity Types · Relationship Types · Query Patterns · Document Corpus
A2: Why GraphRAG for corporate services: clients, jurisdictions, ownership chains, and compliance rules form a dense relationship graph that flat vector search cannot traverse correctly.
A3: A — ENTITY TYPES
A4: # | B4: Entity Type | C4: Properties (required) | D4: Properties (optional) | E4: Source System | F4: Uniqueness Key | G4: Update Trigger | H4: Notes
A5: 1 | B5: Client | C5: client_id, full_legal_name, incorporation_date, jurisdiction_of_incorp | D5: trade_name, parent_entity_id, industry_code, risk_rating | E5: CRM / Salesforce | F5: client_id | G5: On onboarding or KYC refresh | H5: Root entity — all mandates hang off this
A6: 2 | B6: Individual | C6: individual_id, full_name, nationality, date_of_birth, passport_number | D6: tax_id, PEP_flag, sanction_flag, address_current | E6: KYC system | F6: individual_id | G6: On onboarding or AML review | H6: Directors, shareholders, UBOs all share this type
A7: 3 | B7: Jurisdiction | C7: jurisdiction_code (ISO 3166), full_name, legal_system_type | D7: tax_treaty_list, FATF_status, substance_requirements | E7: Regulatory feed / manual | F7: jurisdiction_code | G7: On regulatory change | H7: Core to all compliance queries
A8: 4 | B8: Legal_Entity | C8: entity_id, entity_type (LLC/Ltd/Foundation etc), registered_name, registered_number | D8: registered_address, filing_status, share_capital | E8: Registry APIs / CRM | F8: registered_number + jurisdiction_code | G8: On incorporation or change | H8: Can be child or parent of Client
A9: 5 | B9: Service_Mandate | C9: mandate_id, service_type, start_date, status | D9: end_date, renewal_date, fee_schedule_id, assigned_officer | E9: CRM | F9: mandate_id | G9: On engagement or status change | H9: Links Client to Service_Type to Officer
A10: 6 | B10: Service_Type | C10: service_code, service_name, category | D10: required_jurisdictions, typical_timeline, compliance_requirements | E10: Internal product catalog | F10: service_code | G10: On product change | H10: Formation · Banking intro · Accounting · Compliance etc
A11: 7 | B11: Regulator | C11: regulator_id, name, jurisdiction_code, authority_type | D11: contact_portal, reporting_deadlines, key_regulations | E11: Manual / regulatory feed | F11: regulator_id | G11: Annual review | H11: Linked to Jurisdiction and Service_Type
A12: 8 | B12: Document | C12: doc_id, doc_type, issue_date, issuing_authority | D12: expiry_date, related_entity_id, file_ref | E12: DMS / Drive | F12: doc_id | G12: On document upload or expiry | H12: Certs of Incorp, UBO declarations, bank letters etc
A13: 9 | B13: Bank_Account | C13: account_id, bank_name, jurisdiction_code, account_type, status | D13: currency, iban, swift, opening_date | E13: Banking intro CRM | F13: account_id | G13: On account open/close | H13: Linked to Legal_Entity and Service_Mandate
A14: 10 | B14: Officer | C14: officer_id, name, role_type (director/secretary/nominee) | D14: effective_date, resignation_date, entity_id | E14: Registry / CRM | F14: officer_id + entity_id | G14: On appointment/change | H14: Individual acting as officer of Legal_Entity
A16: B — RELATIONSHIP TYPES
A17: # | B17: Relationship Type | C17: From Entity | D17: To Entity | E17: Cardinality | F17: Properties | G17: Business Meaning | H17: Query Example
A18: 1 | B18: OWNS | C18: Individual / Legal_Entity | D18: Legal_Entity | E18: Many-to-many (with ownership %) | F18: ownership_pct, share_class, effective_date | G18: Shareholding / UBO chain — traverse to find ultimate beneficial owner | H18: MATCH (i:Individual)-[:OWNS*1..5]->(e:Legal_Entity {id:'X'}) RETURN i
A19: 2 | B19: IS_DIRECTOR_OF | C19: Individual | D19: Legal_Entity | E19: Many-to-many | F19: role, appointment_date, resignation_date | G19: Directorship — used for conflict-of-interest checks | H19: Find all entities where Individual X is director
A20: 3 | B20: IS_UBO_OF | C20: Individual | D20: Legal_Entity | E20: Many-to-many (threshold ≥25%) | F20: beneficial_pct, declaration_date | G20: Ultimate beneficial ownership — direct or derived via OWNS chain | H20: MATCH (i)-[:IS_UBO_OF]->(e) WHERE e.risk_rating='HIGH'
A21: 4 | B21: INCORPORATED_IN | C21: Legal_Entity | D21: Jurisdiction | E21: Many-to-one | F21: incorporation_date, registration_number | G21: Links entity to its home jurisdiction and its regulator | H21: Find all clients incorporated in BVI with banking in CH
A22: 5 | B22: HAS_MANDATE | C22: Client | D22: Service_Mandate | E22: One-to-many | F22: signed_date, fee, currency | G22: Active service engagements — filter by status for pipeline | H22: Find all active mandates for accounting service expiring Q1
A23: 6 | B23: HOLDS_ACCOUNT_AT | C23: Legal_Entity | D23: Bank_Account | E23: One-to-many | F23: opening_date, primary_flag | G23: Bank relationship — for banking intro and compliance reporting | H23: Find entities with no active bank account after 6 months
A24: 7 | B24: GOVERNED_BY | C24: Legal_Entity / Service_Type | D24: Regulator | E24: Many-to-many | F24: regulation_ref, effective_date | G24: Compliance jurisdiction mapping | H24: Which regulators apply to a Singapore-incorporated fund?
A25: 8 | B25: CONFLICTS_WITH | C25: Individual / Legal_Entity | D25: Individual / Legal_Entity | E25: Many-to-many | F25: conflict_type, identified_date, resolution_status | G25: Conflict of interest — blocks new mandates until resolved | H25: Before onboarding: MATCH conflict paths between new client and existing
A26: 9 | B26: RELATED_DOCUMENT | C26: Any entity | D26: Document | E26: Many-to-many | F26: doc_role (e.g. cert_of_incorp, bank_letter) | G26: Links entities to their supporting documents | H26: Find all expired documents for entities in Annual Return due list
A27: 10 | B27: REFERS_TO | C27: Document | D27: Jurisdiction / Regulator / Service_Type | E27: Many-to-many | F27: reference_type, section | G27: Connects regulatory documents to the entities they govern | H27: Find all documents that reference FATF Recommendation 24
A29: C — CANONICAL QUERY PATTERNS (business questions the graph must answer)
A30: # | B30: Business Question | C30: Entities Traversed | D30: Relationship Path | E30: Output | F30: Vanilla RAG fails because… | G30: Priority | H30: Agent that uses this
A31: 1 | B31: Who is the Ultimate Beneficial Owner of Client X? | C31: Client → Legal_Entity → Individual | D31: OWNS (multi-hop, up to 5 levels) | E31: Individual(s) with ≥25% beneficial ownership | F31: Ownership chain is in multiple documents; flat search cannot traverse hops | G31: CRITICAL | H31: Compliance agent
A32: 2 | B32: Does Individual Y appear in any existing client structure before onboarding? | C32: Individual → Legal_Entity → Client | D32: IS_DIRECTOR_OF / IS_UBO_OF / OWNS | E32: Existing client connections + conflict flag | F32: Individual may be named differently across docs; graph uses entity IDs | G32: CRITICAL | H32: Compliance agent
A33: 3 | B33: Which mandates are due for renewal in the next 90 days? | C33: Client → Service_Mandate | D33: HAS_MANDATE (filter on renewal_date) | E33: Mandate list with client name, service type, officer | F33: Dates scattered across CRM and documents; no unified retrieval | G33: HIGH | H33: Orchestrator + Operations agent
A34: 4 | B34: Which jurisdiction rules apply to a Singapore-incorporated fund selling to EU investors? | C34: Jurisdiction → Regulator → Document | D34: INCORPORATED_IN + GOVERNED_BY + REFERS_TO | E34: Regulation list per jurisdiction pair | F34: Multi-jurisdiction answer requires joining 3+ document sources | G34: HIGH | H34: Research agent
A35: 5 | B35: Find all entities where Document X (passport) is expiring within 30 days | C35: Document → Individual → Legal_Entity / Officer | D35: RELATED_DOCUMENT (filter expiry_date) | E35: Entity list + contact details + responsible officer | F35: Expiry info is buried in unstructured document fields | G35: HIGH | H35: Compliance agent
A36: 6 | B36: What banking options exist for a UAE-resident setting up a BVI company? | C36: Jurisdiction → Bank_Account → Legal_Entity | D36: INCORPORATED_IN + HOLDS_ACCOUNT_AT (filter by client profile) | E36: Bank shortlist with success rate from mandate history | F36: Answer requires combining jurisdiction rules + historical success data | G36: MEDIUM | H36: Research agent
A37: 7 | B37: Generate a group structure chart for Client X | C37: Client → Legal_Entity (all layers) → Individual | D37: OWNS + IS_DIRECTOR_OF + IS_UBO_OF (full subgraph) | E37: Hierarchical ownership diagram data | F37: Structure spans multiple documents with no single source of truth | G37: HIGH | H37: Drafting agent

Sheet 03_L5_Agent_Specs
A1: L5 — AGENT SPECIFICATIONS · Role · Tools · Memory · Escalation · Risk Level
A2: Each agent has exactly one spec. The orchestrator routes; specialists execute. No agent should have undefined tool access or undefined escalation.
A3: # | B3: Agent Name | C3: Type | D3: Role / Mandate | E3: Tools Permitted | F3: Memory Access | G3: Escalation Trigger → Target | H3: Risk Level | I3: Skills Used | J3: AGENT_SPEC.md Status
A4: 1 | B4: Orchestrator | C4: Router / Planner | D4: Receives all inbound requests. Classifies intent, routes to specialist agents, tracks multi-step job state, assembles final response | E4: All agents (spawn/call), CRM read, Memory read (all types) | F4: Working memory (full); Episodic (client lookup); Semantic (SOP routing rules) | G4: Ambiguous intent → Human intake officer Conflict of interest detected → Compliance agent All agents fail → Human escalation | H4: LOW (routes only, does not execute) | I4: intent_classifier, client_lookup | J4: DRAFT
A5: 2 | B5: Research Agent | C5: Executor — Research | D5: Answers jurisdiction questions, regulatory comparisons, product eligibility checks. Primary consumer of GraphRAG + web search | E5: GraphRAG query, Web search, Regulatory feed API, Document corpus search | F5: Semantic (procedures/regulations); Working memory (current query) | G5: Hallucination risk detected → add human review gate Source conflict → flag for analyst | H5: MEDIUM | I5: jurisdiction_compare, regulation_lookup, entity_eligibility_check | J5: DRAFT
A6: 3 | B6: Drafting Agent | C6: Executor — Document | D6: Generates first-draft documents: engagement letters, structure memos, annual return notices, banking intro letters. Always human-reviewed before send | E6: Document templates (Drive), GraphRAG (entity data pull), CRM read | F6: Episodic (client history for personalization); Procedural (document templates) | G6: Missing required data → pause and request from human High-risk document type → mandatory legal review gate | H6: MEDIUM-HIGH | I6: doc_draft_engagement, doc_draft_banking_intro, structure_chart_gen | J6: DRAFT
A7: 4 | B7: Compliance Agent | C7: Executor — Compliance | D7: Runs KYC/AML checks, UBO traversal, conflict-of-interest detection, sanction screening, document expiry monitoring | E7: GraphRAG (deep traversal), Sanction list API, PEP database API, CRM write (risk flags) | F7: Episodic (full client history); Semantic (compliance rules per jurisdiction) | G7: Sanctions match → immediate human escalation (no auto-action) UBO chain > 5 hops → human review High-risk jurisdiction → compliance officer approval | H7: HIGH — outputs trigger blocking actions | I7: ubo_chain_traverse, sanctions_screen, conflict_check, doc_expiry_scan | J7: DRAFT
A8: 5 | B8: Operations Agent | C8: Executor — Internal Ops | D8: Handles internal workflow tasks: mandate renewal alerts, deadline tracking, officer appointment reminders, reporting package assembly | E8: CRM read/write, Calendar API, Email (send via human-approved template), Drive | F8: Episodic (mandate history); Procedural (SOP for each service type); Semantic (service deadlines) | G8: Missed deadline → alert human officer + escalate to manager Action requires client signature → pause for human | H8: MEDIUM | I8: mandate_renewal_alert, deadline_tracker, report_assembly | J8: DRAFT
A10: AGENT_SPEC.md — Required Sections Template
A11: 1 | B11: 1. Agent identity | E11: name, version, layer (L5), created_date, status (draft/active/deprecated)
A12: 2 | B12: 2. Role statement | E12: One paragraph: what this agent does, what it does NOT do, and why it exists
A13: 3 | B13: 3. System prompt (versioned) | E13: Full system prompt text, version number, change log. Stored in version control.
A14: 4 | B14: 4. Tool access list | E14: Table: tool_name | permission (read/write/execute) | max_calls_per_session | fallback_if_unavailable
A15: 5 | B15: 5. Memory read/write scope | E15: Which memory types this agent reads and writes. What it must NOT persist (e.g. PII in working memory after session ends)
A16: 6 | B16: 6. Input contract | E16: Expected input format, required fields, optional fields, validation rules
A17: 7 | B17: 7. Output contract | E17: Output format, required fields, confidence/uncertainty signaling, how errors are returned
A18: 8 | B18: 8. Escalation rules | E18: Table: trigger_condition | escalation_target | urgency | human_action_required
A19: 9 | B19: 9. Inter-agent routing | E19: Which agents this agent can spawn or call, and under what conditions
A20: 10 | B20: 10. Risk level + approval gate | E20: Risk rating, who must approve outputs before action, audit log requirement
A21: 11 | B21: 11. Eval criteria | E21: Link to EVAL.json, minimum pass rate, last tested date, regression check trigger

Sheet 04_L4_Skills_Workflows
A1: L4 — SKILL CATALOG & WORKFLOW REGISTRY · Corporate Services — Initial Backlog
A2: Each row = one skill. Formula columns auto-calculate complexity score and build priority. Add WORKFLOW.md and EVAL.json links as skills are built.
A3: # | B3: Skill Name (skill-id) | C3: Agent Owner | D3: Type | E3: Trigger Phrases (sample) | F3: Input → Output | G3: Tools / Dependencies | H3: Human Gate? | I3: Impact (1–5) | J3: Effort (1–5) | K3: Priority Score
A4: 1 | B4: jurisdiction-compare | C4: Research Agent | D4: Research | E4: "compare BVI vs Cayman" / "which jurisdiction for a fund?" / "cost comparison" | F4: Jurisdiction pair + client profile → structured comparison table | G4: GraphRAG, Web search, Regulatory feed | H4: No | I4: 5 | J4: 2 | K4: =IFERROR(ROUND(I4*2/J4,1),"-") -> 5
A5: 2 | B5: ubo-chain-traverse | C5: Compliance Agent | D5: Compliance | E5: "find UBO of" / "who ultimately owns" / "beneficial owner check" | F5: Legal_Entity ID → UBO list with ownership percentages | G5: GraphRAG (multi-hop OWNS traversal) | H5: Yes — if chain > 3 hops | I5: 5 | J5: 3 | K5: =IFERROR(ROUND(I5*2/J5,1),"-") -> 3.3
A6: 3 | B6: sanctions-screen | C6: Compliance Agent | D6: Compliance | E6: "screen individual" / "AML check" / "PEP screening" | F6: Individual ID or name → PASS/FAIL + match details | G6: Sanctions list API, PEP database API | H6: Yes — any match | I6: 5 | J6: 2 | K6: =IFERROR(ROUND(I6*2/J6,1),"-") -> 5
A7: 4 | B7: conflict-check | C7: Compliance Agent | D7: Compliance | E7: "conflict of interest" / "can we onboard" / "related party check" | F7: New client profile → conflict flag + existing connections | G7: GraphRAG (IS_DIRECTOR_OF, OWNS paths) | H7: Yes — always | I7: 5 | J7: 3 | K7: =IFERROR(ROUND(I7*2/J7,1),"-") -> 3.3
A8: 5 | B8: doc-draft-engagement-letter | C8: Drafting Agent | D8: Document | E8: "draft engagement letter" / "prepare LOE" / "onboarding letter" | F8: Client ID + service type → engagement letter draft (Word) | G8: GraphRAG (client data), Drive (templates), CRM | H8: Yes — before send | I8: 4 | J8: 2 | K8: =IFERROR(ROUND(I8*2/J8,1),"-") -> 4
A9: 6 | B9: doc-draft-banking-intro | C9: Drafting Agent | D9: Document | E9: "banking introduction letter" / "bank referral letter" | F9: Client ID + target bank → intro letter draft | G9: GraphRAG (entity data), Drive (templates) | H9: Yes — before send | I9: 4 | J9: 2 | K9: =IFERROR(ROUND(I9*2/J9,1),"-") -> 4
A10: 7 | B10: mandate-renewal-alert | C10: Operations Agent | D10: Operations | E10: "mandates expiring" / "renewal pipeline" / "upcoming renewals" | F10: Date range → mandate list with client, service, renewal date, officer | G10: CRM (HAS_MANDATE query), Calendar API | H10: No — alert only | I10: 4 | J10: 1 | K10: =IFERROR(ROUND(I10*2/J10,1),"-") -> 8
A11: 8 | B11: structure-chart-gen | C11: Drafting Agent | D11: Document | E11: "group structure" / "org chart" / "ownership diagram" | F11: Client ID → ownership structure diagram (data for rendering) | G11: GraphRAG (full subgraph OWNS + IS_DIRECTOR_OF) | H11: Yes — client review | I11: 4 | J11: 3 | K11: =IFERROR(ROUND(I11*2/J11,1),"-") -> 2.7
A12: 9 | B12: doc-expiry-scan | C12: Compliance Agent | D12: Compliance | E12: "expiring documents" / "KYC refresh needed" / "expired passport" | F12: Date threshold → list of entities with expiring docs | G12: GraphRAG (RELATED_DOCUMENT filter expiry_date) | H12: No — alert only | I12: 4 | J12: 1 | K12: =IFERROR(ROUND(I12*2/J12,1),"-") -> 8
A13: 10 | B13: regulation-lookup | C13: Research Agent | D13: Research | E13: "what are the rules for" / "substance requirements" / "FATF status" | F13: Jurisdiction + topic → regulation summary with source citations | G13: GraphRAG (Document corpus), Web search | H13: No | I13: 3 | J13: 2 | K13: =IFERROR(ROUND(I13*2/J13,1),"-") -> 3
A14: 11 | B14: entity-eligibility-check | C14: Research Agent | D14: Research | E14: "can a Singapore company open account in" / "eligible for" | F14: Entity profile + product/service → eligibility + requirements | G14: GraphRAG (GOVERNED_BY + INCORPORATED_IN) | H14: No | I14: 3 | J14: 2 | K14: =IFERROR(ROUND(I14*2/J14,1),"-") -> 3
A15: 12 | B15: report-assembly | C15: Operations Agent | D15: Operations | E15: "generate monthly report" / "client portfolio summary" | F15: Officer ID + period → portfolio report (PDF/Excel) | G15: CRM, GraphRAG, Drive | H15: Yes — review before send | I15: 3 | J15: 3 | K15: =IFERROR(ROUND(I15*2/J15,1),"-") -> 2
... A17: 14 | B17: client-lookup | C17: Orchestrator | D17: Data | E17: (internal — triggered on any client mention) | F17: Client name/ID → client profile + active mandates | G17: CRM, GraphRAG | H17: No | I17: 5 | J17: 1 | K17: =IFERROR(ROUND(I17*2/J17,1),"-") -> 10
A19: SKILL.md — Required Sections Template
A20: 1 | B20: name | E20: Unique slug identifier, lowercase-hyphenated. Example: ubo-chain-traverse
A21: 2 | B21: description | E21: 2–3 sentences: WHAT it does, WHEN Claude should trigger it (include specific phrases). Make it slightly 'pushy' — list edge cases that should still trigger it.
A22: 3 | B22: trigger_phrases | E22: List of ≥5 example user phrases or internal signals that should invoke this skill
A23: 4 | B23: input_format | E23: Schema of expected input: field names, types, required/optional, validation rules
A24: 5 | B24: output_format | E24: Schema of output: format (JSON/Markdown/docx/inline), required fields, confidence signaling
A25: 6 | B25: steps | E25: Numbered list of what Claude should do, in order. Reference tools by name. Include conditional branches.
A26: 7 | B26: dependencies | E26: Tools, APIs, MCP servers, other skills this skill calls. Version pin where relevant.
A27: 8 | B27: human_in_loop_gates | E27: Exact conditions that pause execution for human review. Who reviews. How to resume.
A28: 9 | B28: eval_criteria | E28: Link to EVAL.json. Minimum pass rate. What constitutes a correct output. Edge cases to test.
A29: 10 | B29: compatibility | E29: Required tools, access permissions, environment assumptions
A30: 11 | B30: version + changelog | E30: Version number, last updated date, change summary

Sheet 05_L2L3_Memory_Tools
A1: L2 — MEMORY SCHEMA · L3 — TOOL REGISTRY & GOVERNANCE
A2: Memory: 4 types with defined schema, retention, and PII rules. Tools: every tool registered, permissioned, and audited before any agent can use it.
A3: L2 — MEMORY ARCHITECTURE
A4: # | B4: Memory Type | C4: What Is Stored | D4: Schema (key fields) | E4: Retention Policy | F4: PII Handling | G4: Agents With Write Access | H4: Notes
A5: 1 | B5: Episodic Memory (per-client session history) | C5: Every interaction with a specific client: questions asked, documents generated, decisions made, flags raised | D5: session_id, client_id, agent_id, timestamp, action_type, input_summary, output_summary, human_approved (bool) | E5: Retain indefinitely while client is active; archive 2 years post-mandate end; delete on client request | F5: Mask PII fields (passport numbers, DOB) in logs; full data in encrypted episodic store only | G5: Orchestrator (read/write), Compliance Agent (read/write), Drafting Agent (read), Operations Agent (read) | H5: Primary source for 'what did we last do for this client?' queries
A6: 2 | B6: Semantic Memory (procedures / SOPs / regulations) | C6: Stable knowledge: jurisdiction rules, service SOPs, compliance procedures, product catalog, fee schedules | D6: doc_id, doc_type, jurisdiction_scope, effective_date, content_chunks (embedded), last_updated | E6: Version-controlled; no deletion — superseded versions archived. Update on regulatory change. | F6: No PII — purely procedural/regulatory content | G6: Research Agent (read), Compliance Agent (read), Operations Agent (read) AI Lead (write) | H6: This is the 'brain' of the firm's operational knowledge; feeds into GraphRAG corpus
A7: 3 | B7: Procedural Memory (skill execution patterns) | C7: How to run each skill: step sequences, tool call patterns, observed failure modes and workarounds | D7: skill_id, execution_pattern, success_rate, common_failures, last_optimized | E7: Update after every 100 skill executions or on skill version change | F7: No PII | G7: All agents (read); AI Lead (write after review) | H7: Used to improve skill performance over time; basis for eval regression checks
A8: 4 | B8: Working Memory (in-flight context) | C8: Current session state: parsed intent, intermediate results, tool outputs, conversation history for current job | D8: job_id, session_id, current_step, tool_outputs (temp), conversation_turns (last 20) | E8: Ephemeral — cleared at end of session or after 24h inactivity | F8: PII permitted during session but MUST be purged at session close; never persisted to long-term store | G8: All agents (read/write during session) | H8: Context window management rules live here: max tokens, summarization triggers, handoff format
A10: L3 — TOOL REGISTRY & GOVERNANCE
A11: # | B11: Tool Name | C11: Type | D11: Auth Method | E11: Agents Permitted (and permission level) | F11: Data Accessed / Written | G11: Rate Limit / Cost | H11: Fallback If Unavailable
A12: 1 | B12: GraphRAG Query Engine | C12: Internal / Knowledge | D12: Internal API key (per-agent scoped) | E12: All agents (READ only) Compliance Agent (READ — deep traversal) AI Lead (ADMIN — schema changes) | F12: Entity graph, relationship graph, document corpus. NO write from agents. | G12: No rate limit (internal); query cost monitored for optimization | H12: Fallback to flat vector search on document corpus (degraded — flag to user)
A13: 2 | B13: Salesforce CRM | C13: MCP Server — CRM | D13: OAuth 2.0, per-agent service account | E13: Orchestrator (READ — client lookup) Operations Agent (READ/WRITE — mandate updates) Compliance Agent (WRITE — risk flags only) | F13: Client records, mandate records, contact data, risk ratings. PII present. | G13: 500 API calls/hour per agent; excess → queue | H13: Cache last 24h read; queue writes; alert human if write backlog > 10
A14: 3 | B14: Google Drive / Docs | C14: MCP Server — DMS | D14: OAuth 2.0, service account per department | E14: Drafting Agent (READ templates, WRITE drafts to staging folder) Operations Agent (READ/WRITE reports) | F14: Document templates, generated drafts. No CRM data written to Drive. | G14: No meaningful rate limit at current scale | H14: Local template cache for Drafting Agent; manual upload if Drive unavailable
A15: 4 | B15: Web Search | C15: External API | D15: API key (shared, monitored) | E15: Research Agent (READ) Compliance Agent (READ — regulatory news) | F15: Public web content only. Must not be used to exfiltrate internal data. | G15: 100 calls/hour; cost ~$0.01/call. Research Agent priority. | H15: Return cached result with staleness warning; flag to human for time-sensitive queries
A16: 5 | B16: Sanctions List API (e.g. Dow Jones / ComplyAdvantage) | C16: External Compliance API | D16: API key — compliance team owns credential | E16: Compliance Agent (READ only) No other agent permitted | F16: Individual/entity names screened against sanctions, PEP, adverse media lists | G16: Per-screen pricing (~$0.10–0.50/screen); monthly budget cap = [INPUT] | H16: BLOCK action — no sanction check = no onboarding. Human must manually screen.
A17: 6 | B17: Calendar / Email API | C17: MCP Server — Communication | D17: OAuth 2.0, per-officer delegated access | E17: Operations Agent (READ calendar, WRITE draft emails to staging — NOT send) No agent can send email directly | F17: Calendar events, email drafts. All email sends require human approval. | G17: Standard API limits; email sends are human-gated so volume low | H17: Queue calendar events; human sends email manually
A18: 7 | B18: Registry APIs (per-jurisdiction: BVI, Cayman, SG, etc.) | C18: External — Registries | D18: Per-registry credentials (varies: API key / portal login) | E18: Research Agent (READ — entity status lookups) Compliance Agent (READ — filing confirmations) | F18: Registered entity status, officer lists, filing dates. Public data. | G18: Varies by registry; most allow ~50–200 calls/day | H18: Manual registry portal lookup; flag as 'unverified via API' in output

Sheet 06_Roadmap_Governance
A1: IMPLEMENTATION ROADMAP & GOVERNANCE · Phased Build Plan · Approval Matrix · Audit Requirements
A2: Build order: L1 GraphRAG schema first (blocks all agents). Then L2 Memory. Then L5 Agents. Then L4 Skills one-by-one with evals. L3 and L6 in parallel.
A3: PHASED BUILD ROADMAP
A4: # | B4: Deliverable | C4: Layer | D4: Phase | E4: Rationale / Dependency | F4: Owner | G4: Est. Effort | H4: Status | I4: Blocks
A5: 1 | B5: GRAPH_SCHEMA.md — Entity + Relationship types defined | C5: L1 | D5: Phase 0 — Foundation (Weeks 1–2) | E5: Everything blocks on this. Agents cannot query what doesn't have a schema. | F5: Data / AI Lead | G5: 3 days | H5: TODO | I5: All agents, all skills
A6: 2 | B6: CORPUS_INDEX.md — Initial document sources catalogued | C6: L1 | D6: Phase 0 — Foundation (Weeks 1–2) | E6: Must know what data exists before indexing. | F6: Data / Knowledge | G6: 2 days | H6: TODO | I6: GraphRAG indexing pipeline
A7: 3 | B7: GraphRAG indexing pipeline — initial graph built | C7: L1 | D7: Phase 0 — Foundation (Weeks 1–2) | E7: Populates the knowledge foundation. Without this, agents use flat search. | F7: Engineering | G7: 1–2 weeks | H7: TODO | I7: Research Agent, Compliance Agent
A8: 4 | B8: MEMORY_SCHEMA.md — all 4 types defined | C8: L2 | D8: Phase 0 — Foundation (Weeks 1–2) | E8: Agents need to know what to remember before any session runs. | F8: AI / Engineering | G8: 2 days | H8: TODO | I8: All agents
A9: 5 | B9: TOOL_REGISTRY.md — all tools registered and permissioned | C9: L3 | D9: Phase 1 — Agent Skeleton (Weeks 3–4) | E9: Agents cannot call tools that aren't registered. Governance gate. | F9: Engineering / IT | G9: 3 days | H9: TODO | I9: All agents
A10: 6 | B10: AGENT_SPEC.md — Orchestrator | C10: L5 | D10: Phase 1 — Agent Skeleton (Weeks 3–4) | E10: Routing logic must exist before any sub-agent is deployed. | F10: AI Lead | G10: 2 days | H10: TODO | I10: All specialist agents
A11: 7 | B11: AGENT_SPEC.md — Research Agent | C11: L5 | D11: Phase 1 — Agent Skeleton (Weeks 3–4) | E11: Highest usage, lowest risk. Good first agent to validate GraphRAG queries. | F11: AI / Ops | G11: 2 days | H11: TODO | I11: jurisdiction-compare, regulation-lookup
A12: 8 | B12: AGENT_SPEC.md — Compliance Agent | C12: L5 | D12: Phase 1 — Agent Skeleton (Weeks 3–4) | E12: High risk — needs full spec + approval before any live use. | F12: AI / Compliance | G12: 3 days | H12: TODO | I12: sanctions-screen, ubo-chain-traverse, conflict-check
A13: 9 | B13: SKILL.md + EVAL.json — intent-classifier | C13: L4 | D13: Phase 2 — First Skills (Weeks 5–6) | E13: Orchestrator uses this first. Simple classification task, fast to eval. | F13: AI Lead | G13: 1 day | H13: TODO | I13: Orchestrator routing
A14: 10 | B14: SKILL.md + EVAL.json — client-lookup | C14: L4 | D14: Phase 2 — First Skills (Weeks 5–6) | E14: Used by almost every workflow. Must be reliable before other skills build on it. | F14: AI / Ops | G14: 1 day | H14: TODO | I14: Most workflows
A15: 11 | B15: SKILL.md + EVAL.json — jurisdiction-compare | C15: L4 | D15: Phase 2 — First Skills (Weeks 5–6) | E15: High value, relatively low risk (research output, human reviews). | F15: Ops / AI | G15: 2 days | H15: TODO | I15: Research Agent
A16: 12 | B16: SKILL.md + EVAL.json — sanctions-screen | C16: L4 | D16: Phase 2 — First Skills (Weeks 5–6) | E16: Required for onboarding. Cannot go live without 100% pass rate on test cases. | F16: Compliance / AI | G16: 3 days | H16: TODO | I16: Compliance Agent, onboarding workflow
... A23: 19 | B23: DEPARTMENT_OS_MAP.md — v1.0 | C23: Cross | D23: Phase 4 — Surface & Governance (Weeks 11–12) | E23: Living document — first version after Phase 3 complete. | F23: AI Lead / Chief of Staff | G23: 2 days | H23: TODO | I23: All Phase 3 docs complete
A25: GOVERNANCE — Approval Matrix (who must sign off before action)
A26: # | B26: Action Type | C26: Risk Level | D26: Auto-Approved? | E26: Approver (human) | F26: Audit Log Required? | G26: Override Possible? | H26: Override Approver | I26: Notes
A27: 1 | B27: Sanctions / PEP screen result — MATCH | C27: CRITICAL | D27: NO | E27: Compliance Officer | F27: YES — immutable log | G27: NO | H27: N/A — must escalate | I27: Match = immediate block. No agent action permitted.
A28: 2 | B28: UBO chain traversal — result delivered to client | C28: HIGH | D28: NO | E28: Compliance Officer | F28: YES | G28: NO | H28: N/A | I28: Must be reviewed before sharing with client
A29: 3 | B29: Conflict-of-interest check — conflict found | C29: HIGH | D29: NO | E29: Senior Partner / Legal | F29: YES — immutable | G29: YES (documented) | H29: Managing Director + Legal | I29: Documented waiver required
A30: 4 | B30: Engagement letter — send to client | C30: MEDIUM-HIGH | D30: NO | E30: Relationship Manager | F30: YES | G30: YES | H30: Department Head | I30: Agent drafts; human reviews and sends
A31: 5 | B31: Banking introduction letter — send | C31: MEDIUM-HIGH | D31: NO | E31: Relationship Manager | F31: YES | G31: YES | H31: Department Head | I31: Agent drafts; human reviews and sends
A32: 6 | B32: Mandate renewal alert — send internal notification | C32: LOW | D32: YES | E32: None (automated) | F32: YES (system log) | G32: YES | H32: Operations Manager | I32: Alert only; no client-facing action
A33: 7 | B33: Research output — share with client | C33: MEDIUM | D33: NO | E33: Analyst / Relationship Manager | F33: YES | G33: YES | H33: Senior Analyst | I33: All research outputs reviewed for accuracy
A34: 8 | B34: New entity added to GraphRAG schema | C34: HIGH | D34: NO | E34: AI Lead + Data Lead | F34: YES | G34: NO | H34: N/A — committee decision | I34: Schema changes affect all agents
A35: 9 | B35: New skill deployed to production | C35: MEDIUM | D35: NO | E35: AI Lead (eval pass rate confirmed) | F35: YES | G35: NO | H35: N/A | I35: Requires EVAL.json pass rate ≥90% documented
A36: 10 | B36: New agent deployed to production | C36: HIGH | D36: NO | E36: AI Lead + Compliance Officer | F36: YES | G36: NO | H36: N/A | I36: Requires AGENT_SPEC.md complete + penetration test

Sheet 07_Dashboard
A1: ARCHITECTURE STATUS DASHBOARD · Live Tracker
B3: Total deliverables | D3: Completed (DONE) | F3: In Progress | H3: Blocked
B4: =COUNTA('06_Roadmap_Governance'!B5:B23) -> 19 | D4: =COUNTIF('06_Roadmap_Governance'!H5:H23,"DONE") -> 0 | F4: =COUNTIF('06_Roadmap_Governance'!H5:H23,"IN PROGRESS") -> 0 | H4: =COUNTIF('06_Roadmap_Governance'!H5:H23,"BLOCKED") -> 0
B7: TODO | D7: % Complete | F7: Skills defined | H7: Agents defined
B8: =COUNTIF('06_Roadmap_Governance'!H5:H23,"TODO") -> 19 | D8: =IFERROR(COUNTIF('06_Roadmap_Governance'!H5:H23,"DONE")/COUNTA('06_Roadmap_Governance'!B5:B23),0) -> 0 | F8: =COUNTA('04_L4_Skills_Workflows'!B4:B17) -> 14 | H8: =COUNTA('03_L5_Agent_Specs'!B4:B8) -> 5
B12: Layer completion status — update Status column in 06_Roadmap_Governance to track
B13: Layer | C13: Name | D13: # Deliverables | E13: Done | F13: % Done | G13: Critical Blocker? | H13: Status | I13: Doc Template Owner
B14: L1 | C14: Knowledge Foundation (GraphRAG) | D14: 3 | E14: 0 | F14: =IFERROR(E14/D14,0) -> 0 | G14: YES | H14: TODO | I14: Data / Knowledge
B15: L2 | C15: Memory & Context | D15: 1 | E15: 0 | F15: =IFERROR(E15/D15,0) -> 0 | G15: No | H15: TODO | I15: AI / Engineering
B16: L3 | C16: Integration & Tool Governance | D16: 1 | E16: 0 | F16: =IFERROR(E16/D16,0) -> 0 | G16: No | H16: TODO | I16: Engineering / IT
B17: L4 | C17: Skill & Workflow Layer | D17: 8 | E17: 0 | F17: =IFERROR(E17/D17,0) -> 0 | G17: No | H17: TODO | I17: Operations / AI
B18: L5 | C18: Agent Layer | D18: 5 | E18: 0 | F18: =IFERROR(E18/D18,0) -> 0 | G18: YES | H18: TODO | I18: AI Lead
B19: L6 | C19: Interaction Surface | D19: 1 | E19: 0 | F19: =IFERROR(E19/D19,0) -> 0 | G19: No | H19: TODO | I19: Product / Design
B20: Cross | C20: Governance + OS Map | D20: 2 | E20: 0 | F20: =IFERROR(E20/D20,0) -> 0 | G20: No | H20: TODO | I20: AI Lead / Legal
